[
  {
    "id": 1,
    "rollNumber": "MNK001",
    "name": "Aarav Kumar",
    "class": "5th",
    "age": 11,
    "gender": "Male",
    "attendance": 85,
    "contact": "+91 98765 43210",
    "address": "House No. 23, Munirka Village, New Delhi",
    "guardian": "Rajesh Kumar (Father)",
    "project": "munirka"
  },
  {
    "id": 2,
    "rollNumber": "MNK002",
    "name": "Priya Sharma",
    "class": "6th",
    "age": 12,
    "gender": "Female",
    "attendance": 92,
    "contact": "+91 98765 43211",
    "address": "House No. 45, Munirka Village, New Delhi",
    "guardian": "Sunita Sharma (Mother)",
    "project": "munirka"
  },
  {
    "id": 3,
    "rollNumber": "MNK003",
    "name": "Rohan Verma",
    "class": "5th",
    "age": 10,
    "gender": "Male",
    "attendance": 78,
    "contact": "+91 98765 43212",
    "address": "House No. 67, Munirka Village, New Delhi",
    "guardian": "Amit Verma (Father)",
    "project": "munirka"
  },
  {
    "id": 4,
    "rollNumber": "MNK004",
    "name": "Ananya Singh",
    "class": "7th",
    "age": 13,
    "gender": "Female",
    "attendance": 95,
    "contact": "+91 98765 43213",
    "address": "House No. 12, Munirka Village, New Delhi",
    "guardian": "Kavita Singh (Mother)",
    "project": "munirka"
  },
  {
    "id": 5,
    "rollNumber": "MNK005",
    "name": "Arjun Patel",
    "class": "6th",
    "age": 12,
    "gender": "Male",
    "attendance": 68,
    "contact": "+91 98765 43214",
    "address": "House No. 89, Munirka Village, New Delhi",
    "guardian": "Mahesh Patel (Father)",
    "project": "munirka"
  },
  {
    "id": 6,
    "rollNumber": "KHK001",
    "name": "Riya Gupta",
    "class": "5th",
    "age": 11,
    "gender": "Female",
    "attendance": 88,
    "contact": "+91 98765 43215",
    "address": "House No. 34, Khirki Village, New Delhi",
    "guardian": "Pooja Gupta (Mother)",
    "project": "khirki"
  },
  {
    "id": 7,
    "rollNumber": "KHK002",
    "name": "Karan Reddy",
    "class": "7th",
    "age": 13,
    "gender": "Male",
    "attendance": 72,
    "contact": "+91 98765 43216",
    "address": "House No. 56, Khirki Village, New Delhi",
    "guardian": "Ramesh Reddy (Father)",
    "project": "khirki"
  },
  {
    "id": 8,
    "rollNumber": "KHK003",
    "name": "Sneha Das",
    "class": "6th",
    "age": 12,
    "gender": "Female",
    "attendance": 90,
    "contact": "+91 98765 43217",
    "address": "House No. 78, Khirki Village, New Delhi",
    "guardian": "Anita Das (Mother)",
    "project": "khirki"
  },
  {
    "id": 9,
    "rollNumber": "HKS001",
    "name": "Vivek Joshi",
    "class": "5th",
    "age": 10,
    "gender": "Male",
    "attendance": 45,
    "contact": "+91 98765 43218",
    "address": "House No. 91, Hauz Khas, New Delhi",
    "guardian": "Suresh Joshi (Father)",
    "project": "hauz-khas"
  },
  {
    "id": 10,
    "rollNumber": "HKS002",
    "name": "Diya Agarwal",
    "class": "7th",
    "age": 13,
    "gender": "Female",
    "attendance": 87,
    "contact": "+91 98765 43219",
    "address": "House No. 15, Hauz Khas, New Delhi",
    "guardian": "Neha Agarwal (Mother)",
    "project": "hauz-khas"
  },
  {
    "id": 11,
    "rollNumber": "MNK006",
    "name": "Aditya Mehta",
    "class": "6th",
    "age": 12,
    "gender": "Male",
    "attendance": 81,
    "contact": "+91 98765 43220",
    "address": "House No. 101, Munirka Village, New Delhi",
    "guardian": "Deepak Mehta (Father)",
    "project": "munirka"
  },
  {
    "id": 12,
    "rollNumber": "MNK007",
    "name": "Sakshi Rao",
    "class": "5th",
    "age": 11,
    "gender": "Female",
    "attendance": 94,
    "contact": "+91 98765 43221",
    "address": "House No. 52, Munirka Village, New Delhi",
    "guardian": "Lakshmi Rao (Mother)",
    "project": "munirka"
  }
]
